domain_model/__init__.py
domain_model/domain_model.py
domain_model/exceptions.py
domain_model-0.3.1.dist-info/LICENSE
domain_model-0.3.1.dist-info/METADATA
domain_model-0.3.1.dist-info/WHEEL
domain_model-0.3.1.dist-info/top_level.txt
domain_model-0.3.1.dist-info/RECORD
